Proxi-1.0.dist-info/DESCRIPTION.rst
Proxi-1.0.dist-info/METADATA
Proxi-1.0.dist-info/RECORD
Proxi-1.0.dist-info/WHEEL
Proxi-1.0.dist-info/metadata.json
Proxi-1.0.dist-info/top_level.txt
proxi/algorithms/__init__.py
proxi/algorithms/knng.py
proxi/algorithms/pairwise.py
proxi/algorithms/pknng.py
proxi/algorithms/rng.py
proxi/utils/__init__.py
proxi/utils/distance.py
proxi/utils/misc.py
proxi/utils/process.py
proxi/utils/similarity.py
