Metadata-Version: 2.0
Name: Proxi
Version: 1.0
Summary: Python Library for Proximity Network Inference.
Home-page: http://ailab.ist.psu.edu/yasser/
Author: Yasser El-Manzalawy
Author-email: yasser@idsrlab.com
Maintainer: Yasser El-Manzalawy
Maintainer-email: yasser@idsrlab.com
License: BSD
Platform: any
Requires-Dist: scikit-learn
Requires-Dist: networkx
